image_processing_on/__init__.py
image_processing_on/processing/__init__.py
image_processing_on/processing/combination.py
image_processing_on/processing/transformation.py
image_processing_on/utils/__init__.py
image_processing_on/utils/io.py
image_processing_on/utils/plot.py
image_processing_on-0.0.7.dist-info/METADATA
image_processing_on-0.0.7.dist-info/WHEEL
image_processing_on-0.0.7.dist-info/top_level.txt
image_processing_on-0.0.7.dist-info/RECORD
