Metadata-Version: 2.1
Name: image-processing-on
Version: 0.0.7
Summary: Image Processing Package using skimage
Home-page: https://github.com/maisonhenrique/image-processing-package
Author: Maison Henrique
License: UNKNOWN
Platform: UNKNOWN
Requires-Python: >=3.5
Requires-Dist: matplotlib
Requires-Dist: numpy
Requires-Dist: scikit-image (>=0.16.1)
